{"Iterators":{"Iterators":{"internalLink":{"count":2,"lastUpdated":1692914003240}}},"branched":{"branched":{"currentFile":{"count":1,"lastUpdated":1691526900667}}},"expression":{"expression":{"currentFile":{"count":2,"lastUpdated":1693375278147}}},"loops":{"loops":{"currentFile":{"count":3,"lastUpdated":1693376960117}}},"statements":{"statements":{"currentFile":{"count":1,"lastUpdated":1693376575711}}},"while":{"while":{"currentFile":{"count":1,"lastUpdated":1693376594422}}},"2d Array":{"2d Array":{"internalLink":{"count":2,"lastUpdated":1693412631929}}},"Arrays":{"Arrays":{"internalLink":{"count":2,"lastUpdated":1693885531400}}},"progress":{"progress":{"currentFile":{"count":1,"lastUpdated":1693681967612}}},"#####":{"#####":{"currentFile":{"count":1,"lastUpdated":1693796382146}}},"Butter":{"Butter":{"currentFile":{"count":2,"lastUpdated":1693798232434}}},"coconut":{"coconut":{"currentFile":{"count":1,"lastUpdated":1693797168838}}},"ingredients":{"ingredients":{"currentFile":{"count":1,"lastUpdated":1693797649158}}},"butter":{"butter":{"currentFile":{"count":2,"lastUpdated":1693798483729}}},"cinnamon":{"cinnamon":{"currentFile":{"count":1,"lastUpdated":1693797821836}}},"powder":{"powder":{"currentFile":{"count":2,"lastUpdated":1693881751148}}},"Optional":{"Optional":{"currentFile":{"count":1,"lastUpdated":1693798267146}}},"Saber":{"Saber":{"currentFile":{"count":1,"lastUpdated":1693800358545}}},"Test Post 1":{"Test Post 1":{"internalLink":{"count":4,"lastUpdated":1693860656740}}},"card test":{"card test":{"internalLink":{"count":1,"lastUpdated":1693848933533}}},"Projects":{"Projects":{"internalLink":{"count":1,"lastUpdated":1693851715033}}},"Pogglewash":{"Pogglewash":{"internalLink":{"count":1,"lastUpdated":1693851722490}}},"Test Post 2":{"Test Post 2":{"internalLink":{"count":1,"lastUpdated":1693861046771}}},"Conditions":{"Conditions":{"internalLink":{"count":1,"lastUpdated":1693881516502}}},"optional":{"optional":{"currentFile":{"count":1,"lastUpdated":1693881736435}}},"Cookies":{"Cookies":{"internalLink":{"count":1,"lastUpdated":1693882149501}}}}